{
  "timeframe": "30min",
  "entries_total_replayed": 1646,
  "first_exits_same_bar": 1152,
  "potential_second_breakout_bars": 778,
  "potential_second_breakout_pct_of_entries": 47.2661,
  "potential_second_breakout_pct_of_same_bar_exits": 67.5347,
  "after_first_exit_reason": {
    "InitialSL": 434,
    "TrailingSL": 344
  },
  "first_exit_reasons_same_bar": {
    "InitialSL": 808,
    "TrailingSL": 344
  },
  "second_side": {
    "short": 406,
    "long": 372
  },
  "second_shape": {
    "original_t2": 614,
    "t3_swing": 164
  },
  "first_side_for_second": {
    "short": 406,
    "long": 372
  },
  "same_side_vs_opposite": {
    "same_side": 748,
    "opposite_side": 30
  },
  "examples": [
    {
      "signal_bar_time": "2026-01-01 07:00:00+00:00",
      "first_entry_time": "2026-01-01 07:11:33+00:00",
      "first_entry_side": "short",
      "first_entry_shape": "original_t2",
      "first_exit_time": "2026-01-01 07:12:35+00:00",
      "first_exit_reason": "InitialSL",
      "second_breakout_time": "2026-01-01 07:13:04+00:00",
      "second_side": "short",
      "second_shape": "original_t2",
      "same_side": true,
      "seconds_after_exit": 29.0
    },
    {
      "signal_bar_time": "2026-01-01 09:00:00+00:00",
      "first_entry_time": "2026-01-01 09:12:38+00:00",
      "first_entry_side": "long",
      "first_entry_shape": "original_t2",
      "first_exit_time": "2026-01-01 09:20:22+00:00",
      "first_exit_reason": "TrailingSL",
      "second_breakout_time": "2026-01-01 09:20:23+00:00",
      "second_side": "long",
      "second_shape": "original_t2",
      "same_side": true,
      "seconds_after_exit": 1.0
    },
    {
      "signal_bar_time": "2026-01-01 15:00:00+00:00",
      "first_entry_time": "2026-01-01 15:15:27+00:00",
      "first_entry_side": "long",
      "first_entry_shape": "t3_swing",
      "first_exit_time": "2026-01-01 15:16:30+00:00",
      "first_exit_reason": "TrailingSL",
      "second_breakout_time": "2026-01-01 15:16:31+00:00",
      "second_side": "long",
      "second_shape": "t3_swing",
      "same_side": true,
      "seconds_after_exit": 1.0
    },
    {
      "signal_bar_time": "2026-01-01 16:00:00+00:00",
      "first_entry_time": "2026-01-01 16:11:37+00:00",
      "first_entry_side": "short",
      "first_entry_shape": "original_t2",
      "first_exit_time": "2026-01-01 16:12:04+00:00",
      "first_exit_reason": "InitialSL",
      "second_breakout_time": "2026-01-01 16:17:12+00:00",
      "second_side": "short",
      "second_shape": "original_t2",
      "same_side": true,
      "seconds_after_exit": 308.0
    },
    {
      "signal_bar_time": "2026-01-01 17:00:00+00:00",
      "first_entry_time": "2026-01-01 17:11:41+00:00",
      "first_entry_side": "long",
      "first_entry_shape": "original_t2",
      "first_exit_time": "2026-01-01 17:21:56+00:00",
      "first_exit_reason": "TrailingSL",
      "second_breakout_time": "2026-01-01 17:21:57+00:00",
      "second_side": "long",
      "second_shape": "original_t2",
      "same_side": true,
      "seconds_after_exit": 1.0
    },
    {
      "signal_bar_time": "2026-01-01 19:30:00+00:00",
      "first_entry_time": "2026-01-01 19:38:08+00:00",
      "first_entry_side": "long",
      "first_entry_shape": "original_t2",
      "first_exit_time": "2026-01-01 19:52:54+00:00",
      "first_exit_reason": "TrailingSL",
      "second_breakout_time": "2026-01-01 19:52:55+00:00",
      "second_side": "long",
      "second_shape": "original_t2",
      "same_side": true,
      "seconds_after_exit": 1.0
    },
    {
      "signal_bar_time": "2026-01-01 21:00:00+00:00",
      "first_entry_time": "2026-01-01 21:13:01+00:00",
      "first_entry_side": "long",
      "first_entry_shape": "original_t2",
      "first_exit_time": "2026-01-01 21:16:01+00:00",
      "first_exit_reason": "InitialSL",
      "second_breakout_time": "2026-01-01 21:26:34+00:00",
      "second_side": "long",
      "second_shape": "original_t2",
      "same_side": true,
      "seconds_after_exit": 633.0
    },
    {
      "signal_bar_time": "2026-01-01 22:00:00+00:00",
      "first_entry_time": "2026-01-01 22:02:46+00:00",
      "first_entry_side": "long",
      "first_entry_shape": "original_t2",
      "first_exit_time": "2026-01-01 22:08:36+00:00",
      "first_exit_reason": "TrailingSL",
      "second_breakout_time": "2026-01-01 22:08:37+00:00",
      "second_side": "long",
      "second_shape": "original_t2",
      "same_side": true,
      "seconds_after_exit": 1.0
    }
  ],
  "build_stats": {
    "raw_tick_rows": 539965711,
    "kept_tick_rows": 539965711,
    "sparse_second_rows": 9718393,
    "continuous_second_rows": 10368000,
    "first_second": "2026-01-01T00:00:00+00:00",
    "last_second": "2026-04-30T23:59:59+00:00"
  },
  "elapsed_seconds": 620.7
}